pyaslreport/__init__.py
pyaslreport/main.py
pyaslreport/cli/__init__.py
pyaslreport/cli/generate_report.py
pyaslreport/converters/__init__.py
pyaslreport/converters/dicom_to_nifti_converter.py
pyaslreport/core/__init__.py
pyaslreport/core/config.py
pyaslreport/core/exceptions.py
pyaslreport/core/logging.py
pyaslreport/core/config/allowed_file_types.yaml
pyaslreport/core/config/schemas/consistency_schema.yaml
pyaslreport/core/config/schemas/major_error_schema.yaml
pyaslreport/core/config/schemas/recommended_condition_schema.yaml
pyaslreport/core/config/schemas/recommended_validator_schema.yaml
pyaslreport/core/config/schemas/required_condition_schema.yaml
pyaslreport/core/config/schemas/required_validator_schema.yaml
pyaslreport/enums/__init__.py
pyaslreport/enums/modaliy_enum.py
pyaslreport/io/__init__.py
pyaslreport/io/readers/__init__.py
pyaslreport/io/readers/file_reader.py
pyaslreport/io/readers/nifti_reader.py
pyaslreport/io/readers/yaml_reader.py
pyaslreport/io/writers/__init__.py
pyaslreport/io/writers/json_writer.py
pyaslreport/io/writers/report_writer.py
pyaslreport/io/writers/tsv_writer.py
pyaslreport/modalities/__init__.py
pyaslreport/modalities/base_processor.py
pyaslreport/modalities/base_validator.py
pyaslreport/modalities/registry.py
pyaslreport/modalities/asl/__init__.py
pyaslreport/modalities/asl/constants.py
pyaslreport/modalities/asl/processor.py
pyaslreport/modalities/asl/report_generator.py
pyaslreport/modalities/asl/utils.py
pyaslreport/modalities/asl/validator.py
pyaslreport/modalities/asl/validators/__init__.py
pyaslreport/modalities/asl/validators/base_asl_validator.py
pyaslreport/modalities/asl/validators/boolean_validator.py
pyaslreport/modalities/asl/validators/consistency_validator.py
pyaslreport/modalities/asl/validators/json_validator.py
pyaslreport/modalities/asl/validators/number_array_validator.py
pyaslreport/modalities/asl/validators/number_or_number_array_validator.py
pyaslreport/modalities/asl/validators/number_validator.py
pyaslreport-0.0.3.dist-info/licenses/LICENSE
pyaslreport-0.0.3.dist-info/METADATA
pyaslreport-0.0.3.dist-info/WHEEL
pyaslreport-0.0.3.dist-info/top_level.txt
pyaslreport-0.0.3.dist-info/RECORD
