Metadata-Version: 2.4
Name: pyaslreport
Version: 0.0.3
Summary: A Python package for generating methods sections in for ASL parameters.
Author-email: Ibrahim Abdelazim <ibrahim.abdelazim@fau.de>
License-Expression: MIT
Requires-Python: >=3.7
License-File: LICENSE
Requires-Dist: PyYAML~=6.0.2
Requires-Dist: numpy~=2.2.6
Requires-Dist: nibabel~=5.3.2
Requires-Dist: pydicom~=3.0.1
Requires-Dist: dicom2nifti~=2.6.2
Dynamic: license-file
